.gitignore
.travis.yml
README.rst
base.cfg
bootstrap.py
buildout.cfg
setup.py
docs/HISTORY.rst
docs/TODO.rst
src/collective/__init__.py
src/collective.formcriteria.egg-info/PKG-INFO
src/collective.formcriteria.egg-info/SOURCES.txt
src/collective.formcriteria.egg-info/dependency_links.txt
src/collective.formcriteria.egg-info/entry_points.txt
src/collective.formcriteria.egg-info/namespace_packages.txt
src/collective.formcriteria.egg-info/not-zip-safe
src/collective.formcriteria.egg-info/requires.txt
src/collective.formcriteria.egg-info/top_level.txt
src/collective/formcriteria/README.rst
src/collective/formcriteria/__init__.py
src/collective/formcriteria/comma.pt
src/collective/formcriteria/comma.py
src/collective/formcriteria/configure.zcml
src/collective/formcriteria/contained.py
src/collective/formcriteria/deprecated.zcml
src/collective/formcriteria/formcriteria.css
src/collective/formcriteria/grouped.pt
src/collective/formcriteria/grouped.py
src/collective/formcriteria/interfaces.py
src/collective/formcriteria/sort.py
src/collective/formcriteria/testing.py
src/collective/formcriteria/testing.zcml
src/collective/formcriteria/tests.py
src/collective/formcriteria/topic.py
src/collective/formcriteria/columns/BBB-folder_contents.pt
src/collective/formcriteria/columns/README.rst
src/collective/formcriteria/columns/__init__.py
src/collective/formcriteria/columns/browser.py
src/collective/formcriteria/columns/configure.zcml
src/collective/formcriteria/columns/content.py
src/collective/formcriteria/columns/folder_contents.pt
src/collective/formcriteria/columns/form.py
src/collective/formcriteria/columns/setuphandlers.py
src/collective/formcriteria/columns/utils.py
src/collective/formcriteria/criteria/__init__.py
src/collective/formcriteria/criteria/boolean.py
src/collective/formcriteria/criteria/boolean.rst
src/collective/formcriteria/criteria/checkbox.py
src/collective/formcriteria/criteria/checkbox.rst
src/collective/formcriteria/criteria/comma.py
src/collective/formcriteria/criteria/comma.rst
src/collective/formcriteria/criteria/common.py
src/collective/formcriteria/criteria/context
src/collective/formcriteria/criteria/context.py
src/collective/formcriteria/criteria/context.rst
src/collective/formcriteria/criteria/date.py
src/collective/formcriteria/criteria/date.rst
src/collective/formcriteria/criteria/daterange.py
src/collective/formcriteria/criteria/daterange.rst
